hgdistver.py
hgdistver-0.25.dist-info/top_level.txt
hgdistver-0.25.dist-info/entry_points.txt
hgdistver-0.25.dist-info/METADATA
hgdistver-0.25.dist-info/DESCRIPTION.rst
hgdistver-0.25.dist-info/metadata.json
hgdistver-0.25.dist-info/WHEEL
hgdistver-0.25.dist-info/RECORD
