Metadata-Version: 2.0
Name: hgdistver
Version: 0.25
Summary: utility to generate python package version infos from mercurial/git tags
Home-page: http://bitbucket.org/RonnyPfannschmidt/hgdistver/
Author: Ronny Pfannschmidt
Author-email: opensource@ronnypfannschmidt.de
License: MIT
Platform: UNKNOWN
Classifier: Development Status :: 4 - Beta
Classifier: Intended Audience :: Developers
Classifier: License :: OSI Approved :: MIT License
Classifier: Topic :: Software Development :: Libraries
Classifier: Topic :: Software Development :: Version Control
Classifier: Topic :: System :: Software Distribution
Classifier: Topic :: Utilities
Provides-Extra: files
